TradeTide/__init__.py
TradeTide/_version.py
TradeTide/backtester.py
TradeTide/binary/__init__.py
TradeTide/binary/interface_backtester.cp310-win_amd64.pyd
TradeTide/binary/interface_capital_management.cp310-win_amd64.pyd
TradeTide/binary/interface_exit_strategy.cp310-win_amd64.pyd
TradeTide/binary/interface_indicators.cp310-win_amd64.pyd
TradeTide/binary/interface_market.cp310-win_amd64.pyd
TradeTide/binary/interface_metrics.cp310-win_amd64.pyd
TradeTide/binary/interface_portfolio.cp310-win_amd64.pyd
TradeTide/binary/interface_position.cp310-win_amd64.pyd
TradeTide/binary/interface_position_collection.cp310-win_amd64.pyd
TradeTide/binary/interface_record.cp310-win_amd64.pyd
TradeTide/binary/interface_signal.cp310-win_amd64.pyd
TradeTide/binary/interface_state.cp310-win_amd64.pyd
TradeTide/binary/interface_strategy.cp310-win_amd64.pyd
TradeTide/binary/libcpp_backtester.a
TradeTide/binary/libcpp_base_indicator.a
TradeTide/binary/libcpp_bollinger_bands.a
TradeTide/binary/libcpp_capital_management.a
TradeTide/binary/libcpp_exit_strategy.a
TradeTide/binary/libcpp_market.a
TradeTide/binary/libcpp_metrics.a
TradeTide/binary/libcpp_moving_average_crossings.a
TradeTide/binary/libcpp_portfolio.a
TradeTide/binary/libcpp_position.a
TradeTide/binary/libcpp_position_collection.a
TradeTide/binary/libcpp_record.a
TradeTide/binary/libcpp_relative_momentum_index.a
TradeTide/binary/libcpp_signal.a
TradeTide/binary/libcpp_state.a
TradeTide/binary/libcpp_strategy.a
TradeTide/currencies.py
TradeTide/data/__init__.py
TradeTide/data/CAD_USD.csv
TradeTide/data/CHF_USD.csv
TradeTide/data/EUR_USD.csv
TradeTide/data/GBP_USD.csv
TradeTide/data/JPY_USD.csv
TradeTide/data/utils.py
TradeTide/directories.py
TradeTide/indicators/__init__.py
TradeTide/indicators/base.py
TradeTide/indicators/bollinger_bands.py
TradeTide/indicators/moving_average_crossings.py
TradeTide/indicators/relative_momentum_index.py
TradeTide/loader.py
TradeTide/market.py
TradeTide/portfolio.py
TradeTide/position_collection.py
tradetide-0.2.6.dist-info/METADATA
tradetide-0.2.6.dist-info/WHEEL
tradetide-0.2.6.dist-info/licenses/LICENSE
tradetide-0.2.6.dist-info/RECORD
