Metadata-Version: 2.2
Name: TradeTide
Version: 0.2.6
Summary: A package for stocks market backtesting.
Keywords: backtesting,stocks,market
Author-Email: Martin Poinsinet de Sivry-Houle <martin.poinsinet.de.sivry@gmail.com>
License: MIT License
Classifier: Programming Language :: Python
Classifier: Programming Language :: Python :: 3
Classifier: Programming Language :: Python :: 3.11
Classifier: Programming Language :: Python :: 3.12
Classifier: Programming Language :: Python :: Implementation :: CPython
Classifier: Development Status :: 4 - Beta
Requires-Python: >=3.10
Requires-Dist: pydantic>=2.6.3
Requires-Dist: MPSPlots
Requires-Dist: tabulate
Requires-Dist: pandas
Requires-Dist: GitPython
Requires-Dist: numpy
Requires-Dist: matplotlib
Requires-Dist: mpl-interactions
Provides-Extra: testing
Requires-Dist: pytest>=0.6; extra == "testing"
Requires-Dist: pytest-cov>=2.0; extra == "testing"
Requires-Dist: pytest-json-report==1.5.0; extra == "testing"
Requires-Dist: flake8>=3.9; extra == "testing"
Requires-Dist: coverage==7.10.5; extra == "testing"
Provides-Extra: documentation
Requires-Dist: numpydoc==1.9.0; extra == "documentation"
Requires-Dist: sphinx>=5.1.1; extra == "documentation"
Requires-Dist: sphinx-gallery==0.19.0; extra == "documentation"
Requires-Dist: pydata-sphinx-theme==0.16.1; extra == "documentation"
Requires-Dist: sphinx-rtd-theme==3.0.2; extra == "documentation"
Provides-Extra: dev
Requires-Dist: flake==7.2.0; extra == "dev"
